distlimiter/__init__.py
distlimiter/core.py
distlimiter/admin/__init__.py
distlimiter/admin/api.py
distlimiter/algorithms/__init__.py
distlimiter/algorithms/base.py
distlimiter/algorithms/fixed_window.py
distlimiter/algorithms/hybrid.py
distlimiter/algorithms/leaky_bucket.py
distlimiter/algorithms/sliding_log.py
distlimiter/algorithms/sliding_window.py
distlimiter/algorithms/token_bucket.py
distlimiter/backends/__init__.py
distlimiter/backends/base.py
distlimiter/backends/memory.py
distlimiter/backends/redis.py
distlimiter/middleware/__init__.py
distlimiter/middleware/django.py
distlimiter/middleware/fastapi.py
distlimiter/middleware/flask.py
rate_limiter_dist-0.1.1.dist-info/METADATA
rate_limiter_dist-0.1.1.dist-info/WHEEL
rate_limiter_dist-0.1.1.dist-info/licenses/LICENSE
rate_limiter_dist-0.1.1.dist-info/RECORD
