Metadata-Version: 2.4
Name: rate-limiter-dist
Version: 0.1.1
Summary: A distributed API rate-limiting library for Python with multiple algorithms
Project-URL: Homepage, https://github.com/satyam-kr/distlimiter
Project-URL: Repository, https://github.com/satyam-kr/distlimiter
Project-URL: Documentation, https://github.com/satyam-kr/distlimiter#readme
Author-email: Satyam Kumar <satyamkumarskr@gmail.com>
License: MIT License
License-File: LICENSE
Classifier: Development Status :: 3 - Alpha
Classifier: Intended Audience :: Developers
Classifier: License :: OSI Approved :: MIT License
Classifier: Programming Language :: Python :: 3
Classifier: Programming Language :: Python :: 3.8
Classifier: Programming Language :: Python :: 3.9
Classifier: Programming Language :: Python :: 3.10
Classifier: Programming Language :: Python :: 3.11
Classifier: Programming Language :: Python :: 3.12
Requires-Python: >=3.8
Requires-Dist: aioredis>=2.0.0
Requires-Dist: fastapi>=0.100.0
Requires-Dist: pydantic>=2.0.0
Requires-Dist: redis>=4.0.0
Requires-Dist: uvicorn>=0.20.0
Provides-Extra: all
Requires-Dist: distlimiter[django,fixed-window,flask,hybrid,leaky-bucket,sliding-log,sliding-window,token-bucket]; extra == 'all'
Provides-Extra: django
Requires-Dist: django>=3.2.0; extra == 'django'
Provides-Extra: fixed-window
Provides-Extra: flask
Requires-Dist: flask>=2.0.0; extra == 'flask'
Provides-Extra: hybrid
Provides-Extra: leaky-bucket
Provides-Extra: sliding-log
Provides-Extra: sliding-window
Provides-Extra: token-bucket
